napari_annotation_project/__init__.py
napari_annotation_project/_version.py
napari_annotation_project/folder_list_widget.py
napari_annotation_project/napari.yaml
napari_annotation_project/parameters.py
napari_annotation_project/project.py
napari_annotation_project/project_widget.py
napari_annotation_project/_tests/__init__.py
napari_annotation_project/_tests/test_project.py
napari_annotation_project/_tests/test_project_widget.py
napari_annotation_project-0.2.0.dist-info/licenses/LICENSE
napari_annotation_project-0.2.0.dist-info/METADATA
napari_annotation_project-0.2.0.dist-info/WHEEL
napari_annotation_project-0.2.0.dist-info/entry_points.txt
napari_annotation_project-0.2.0.dist-info/top_level.txt
napari_annotation_project-0.2.0.dist-info/RECORD
