Metadata-Version: 2.4
Name: napari-annotation-project
Version: 0.2.0
Summary: A napari plugin to keep images and annotations as a re-loadable project
Home-page: https://github.com/guiwitz/napari-annotation-project
Author: Guillaume Witz
Author-email: guillaume.witz@unibe.ch
License: BSD-3-Clause
Project-URL: Bug Tracker, https://github.com/guiwitz/napari-annotation-project/issues
Project-URL: Documentation, https://github.com/guiwitz/napari-annotation-project#README.md
Project-URL: Source Code, https://github.com/guiwitz/napari-annotation-project
Project-URL: User Support, https://github.com/guiwitz/napari-annotation-project/issues
Classifier: Development Status :: 2 - Pre-Alpha
Classifier: Intended Audience :: Developers
Classifier: Framework :: napari
Classifier: Topic :: Software Development :: Testing
Classifier: Programming Language :: Python
Classifier: Programming Language :: Python :: 3
Classifier: Programming Language :: Python :: 3.9
Classifier: Programming Language :: Python :: 3.10
Classifier: Programming Language :: Python :: 3.11
Classifier: Programming Language :: Python :: 3.12
Classifier: Operating System :: OS Independent
Classifier: License :: OSI Approved :: BSD License
Requires-Python: >=3.9
License-File: LICENSE
Requires-Dist: numpy
Requires-Dist: PyYAML
Requires-Dist: scikit-image
Provides-Extra: testing
Requires-Dist: tox; extra == "testing"
Requires-Dist: pytest; extra == "testing"
Requires-Dist: pytest-cov; extra == "testing"
Requires-Dist: pytest-qt; extra == "testing"
Requires-Dist: napari; extra == "testing"
Requires-Dist: pyqt5; extra == "testing"
Dynamic: license-file
